multinode/__init__.py
multinode/api_client/__init__.py
multinode/api_client/api/__init__.py
multinode/api_client/api/default_api.py
multinode/api_client/api_client.py
multinode/api_client/api_response.py
multinode/api_client/configuration.py
multinode/api_client/docs/ContainerRepositoryCredentials.md
multinode/api_client/docs/DefaultApi.md
multinode/api_client/docs/ErrorResponse.md
multinode/api_client/docs/ExecutionFinalResultPayload.md
multinode/api_client/docs/ExecutionInfo.md
multinode/api_client/docs/ExecutionLogs.md
multinode/api_client/docs/ExecutionOutcome.md
multinode/api_client/docs/ExecutionSpec.md
multinode/api_client/docs/ExecutionSummary.md
multinode/api_client/docs/ExecutionTemporaryResultPayload.md
multinode/api_client/docs/FunctionInfoForVersion.md
multinode/api_client/docs/FunctionSpec.md
multinode/api_client/docs/FunctionStatus.md
multinode/api_client/docs/HTTPValidationError.md
multinode/api_client/docs/HealthStatus.md
multinode/api_client/docs/InvocationDefinition.md
multinode/api_client/docs/InvocationInfo.md
multinode/api_client/docs/InvocationInfoForFunction.md
multinode/api_client/docs/InvocationStatus.md
multinode/api_client/docs/InvocationsListForFunction.md
multinode/api_client/docs/LocationInner.md
multinode/api_client/docs/ParentInvocationDefinition.md
multinode/api_client/docs/ParentInvocationInfo.md
multinode/api_client/docs/PreparedFunctionDetails.md
multinode/api_client/docs/ProjectInfo.md
multinode/api_client/docs/ProjectsList.md
multinode/api_client/docs/ResourceSpec.md
multinode/api_client/docs/ValidationError.md
multinode/api_client/docs/VersionDefinition.md
multinode/api_client/docs/VersionInfo.md
multinode/api_client/docs/VersionInfoForProject.md
multinode/api_client/docs/VersionsListForProject.md
multinode/api_client/docs/WorkerDetails.md
multinode/api_client/docs/WorkerStatus.md
multinode/api_client/docs/WorkerType.md
multinode/api_client/error_types.py
multinode/api_client/exceptions.py
test_run_multinode-0.0.19.dist-info/METADATA
test_run_multinode-0.0.19.dist-info/WHEEL
test_run_multinode-0.0.19.dist-info/entry_points.txt
test_run_multinode-0.0.19.dist-info/RECORD
